proxy_parse/__init__.py
proxy_parse/exporters.py
proxy_parse/models.py
proxy_parse/proxy/__init__.py
proxy_parse/proxy/abc.py
proxy_parse/proxy/proxy.py
proxy_parse/spiders/__init__.py
proxy_parse/spiders/blog_spot.py
proxy_parse/spiders/free_proxy_list.py
proxy_parse/spiders/hide_my.py
proxy_parse/spiders/proxy_searcher.py
proxy_parse-1.0.1.dist-info/LICENSE
proxy_parse-1.0.1.dist-info/WHEEL
proxy_parse-1.0.1.dist-info/METADATA
proxy_parse-1.0.1.dist-info/RECORD
