Metadata-Version: 2.1
Name: proxy-parse
Version: 1.0.1
Summary: Easy-to-use sync library for handy parsing of proxies
Home-page: https://github.com/krilifon/proxy-parse
License: MIT
Keywords: proxy,parse,proxy-parse,proxies,sync
Author: krilifon
Author-email: krilifongd@gmail.com
Requires-Python: >=3.7,<4.0
Classifier: Environment :: Console
Classifier: Intended Audience :: Developers
Classifier: License :: OSI Approved :: MIT License
Classifier: Programming Language :: Python :: 3
Classifier: Programming Language :: Python :: 3.7
Classifier: Programming Language :: Python :: 3.8
Classifier: Programming Language :: Python :: 3.9
Classifier: Topic :: Software Development :: Libraries :: Python Modules
Classifier: Topic :: Software Development :: Quality Assurance
Classifier: Typing :: Typed
Requires-Dist: Scrapy (>=2.5.1,<3.0.0)
Project-URL: Repository, https://github.com/krilifon/proxy-parse
